credentials/__init__.py
mockers/__init__.py
mockers/pidevclub/__init__.py
mockers/pidevclub/piwebapi/__init__.py
mockers/pidevclub/piwebapi/pi_web_api_client.py
osisoft/__init__.py
osisoft/pidevclub/__init__.py
osisoft/pidevclub/piwebapi/__init__.py
osisoft/pidevclub/piwebapi/api_client.py
osisoft/pidevclub/piwebapi/pi_web_api_client.py
osisoft/pidevclub/piwebapi/rest.py
osisoft/pidevclub/piwebapi/api/__init__.py
osisoft/pidevclub/piwebapi/api/analysis_api.py
osisoft/pidevclub/piwebapi/api/analysis_category_api.py
osisoft/pidevclub/piwebapi/api/analysis_rule_api.py
osisoft/pidevclub/piwebapi/api/analysis_rule_plug_in_api.py
osisoft/pidevclub/piwebapi/api/analysis_template_api.py
osisoft/pidevclub/piwebapi/api/asset_database_api.py
osisoft/pidevclub/piwebapi/api/asset_server_api.py
osisoft/pidevclub/piwebapi/api/attribute_api.py
osisoft/pidevclub/piwebapi/api/attribute_category_api.py
osisoft/pidevclub/piwebapi/api/attribute_template_api.py
osisoft/pidevclub/piwebapi/api/attribute_trait_api.py
osisoft/pidevclub/piwebapi/api/batch_api.py
osisoft/pidevclub/piwebapi/api/calculation_api.py
osisoft/pidevclub/piwebapi/api/channel_api.py
osisoft/pidevclub/piwebapi/api/configuration_api.py
osisoft/pidevclub/piwebapi/api/data_api.py
osisoft/pidevclub/piwebapi/api/data_server_api.py
osisoft/pidevclub/piwebapi/api/element_api.py
osisoft/pidevclub/piwebapi/api/element_category_api.py
osisoft/pidevclub/piwebapi/api/element_template_api.py
osisoft/pidevclub/piwebapi/api/enumeration_set_api.py
osisoft/pidevclub/piwebapi/api/enumeration_value_api.py
osisoft/pidevclub/piwebapi/api/event_frame_api.py
osisoft/pidevclub/piwebapi/api/home_api.py
osisoft/pidevclub/piwebapi/api/point_api.py
osisoft/pidevclub/piwebapi/api/security_identity_api.py
osisoft/pidevclub/piwebapi/api/security_mapping_api.py
osisoft/pidevclub/piwebapi/api/stream_api.py
osisoft/pidevclub/piwebapi/api/stream_set_api.py
osisoft/pidevclub/piwebapi/api/system_api.py
osisoft/pidevclub/piwebapi/api/table_api.py
osisoft.pidevclub.piwebapi_thompsonp17-1.2.0.dist-info/LICENSE.md
osisoft.pidevclub.piwebapi_thompsonp17-1.2.0.dist-info/METADATA
osisoft.pidevclub.piwebapi_thompsonp17-1.2.0.dist-info/WHEEL
osisoft.pidevclub.piwebapi_thompsonp17-1.2.0.dist-info/top_level.txt
osisoft.pidevclub.piwebapi_thompsonp17-1.2.0.dist-info/RECORD
